tidy/__init__.py
tidy/cli.py
tidy/core.py
tidy/exceptions.py
tidy/github.py
tidy/py.typed
tidy/utils.py
tidy/version.py
git_tidy-1.3.0.dist-info/LICENSE
git_tidy-1.3.0.dist-info/METADATA
git_tidy-1.3.0.dist-info/WHEEL
git_tidy-1.3.0.dist-info/entry_points.txt
git_tidy-1.3.0.dist-info/RECORD
