Metadata-Version: 2.1
Name: git-tidy
Version: 1.3.0
Summary: Tidy git commit messages, linting, and logging
Home-page: https://github.com/Opus10/git-tidy
License: BSD-3-Clause
Author: Wes Kendall
Requires-Python: >=3.9.0,<4
Classifier: Intended Audience :: Developers
Classifier: License :: OSI Approved :: BSD License
Classifier: Operating System :: OS Independent
Classifier: Programming Language :: Python
Classifier: Programming Language :: Python :: 3
Classifier: Programming Language :: Python :: 3.9
Classifier: Programming Language :: Python :: 3.10
Classifier: Programming Language :: Python :: 3.11
Classifier: Programming Language :: Python :: 3.12
Classifier: Programming Language :: Python :: 3.13
Classifier: Programming Language :: Python :: 3 :: Only
Requires-Dist: click (>7.0)
Requires-Dist: formaldict (>0.2.0)
Requires-Dist: jinja2 (>2.10.3)
Requires-Dist: packaging (>20.0)
Requires-Dist: python-dateutil (>2.8.1)
Requires-Dist: pyyaml (>=5.1.2,<=5.3.1)
Requires-Dist: requests (>2.22.0)
Project-URL: Documentation, https://git-tidy.readthedocs.io
Project-URL: Repository, https://github.com/Opus10/git-tidy
